gbvcpkg/__init__.py
gbvcpkg/video_player_class.py
gbvcpkg-0.0.4.dist-info/LICENSE
gbvcpkg-0.0.4.dist-info/METADATA
gbvcpkg-0.0.4.dist-info/WHEEL
gbvcpkg-0.0.4.dist-info/top_level.txt
gbvcpkg-0.0.4.dist-info/RECORD
