Metadata-Version: 2.1
Name: gbvcpkg
Version: 0.0.4
Summary: A simple gesture based video controller package
Home-page: https://github.com/dhruvak99/GBVC
Author: Dhruva K
Author-email: dhruva.0107@gmail.com
License: UNKNOWN
Project-URL: Bug Tracker, https://github.com/dhruvak99/GBVC/issues
Platform: UNKNOWN
Classifier: Programming Language :: Python :: 3
Classifier: License :: OSI Approved :: MIT License
Classifier: Operating System :: OS Independent
Requires-Python: >=3.6
License-File: LICENSE
Requires-Dist: tk
Requires-Dist: python-vlc
Requires-Dist: Pillow
Requires-Dist: mediapipe
Requires-Dist: numpy
